py_reminder/__init__.py
py_reminder/py_reminder.py
py_reminder-1.0.2.dist-info/LICENSE
py_reminder-1.0.2.dist-info/METADATA
py_reminder-1.0.2.dist-info/WHEEL
py_reminder-1.0.2.dist-info/top_level.txt
py_reminder-1.0.2.dist-info/RECORD
