Metadata-Version: 2.1
Name: py-reminder
Version: 1.0.2
Summary: A convenient email sender for monitoring your task
Author-email: Wenzhi Ding <wenzhi.ding@foxmail.com>
Project-URL: Homepage, https://github.com/Wenzhi-Ding/py_reminder
Project-URL: Bug Tracker, https://github.com/Wenzhi-Ding/py_reminder/issues
Classifier: Programming Language :: Python :: 3
Classifier: License :: OSI Approved :: MIT License
Classifier: Operating System :: OS Independent
Requires-Python: >=3.6
License-File: LICENSE
